zinfoexport/__init__.py
zinfoexport/blob_client.py
zinfoexport/client.py
zinfoexport/local_client.py
zinfoexport-0.2.8.dist-info/LICENCE.txt
zinfoexport-0.2.8.dist-info/METADATA
zinfoexport-0.2.8.dist-info/WHEEL
zinfoexport-0.2.8.dist-info/top_level.txt
zinfoexport-0.2.8.dist-info/RECORD
