Metadata-Version: 2.1
Name: zinfoexport
Version: 0.2.8
Summary: Package to extract data from z-info (historian)
Home-page: https://gitlab.com/tcadee/z-info-export-client
Author: Tobias Cadée
Author-email: t.cadee@hhsk.nl
License: UNKNOWN
Platform: UNKNOWN
Requires-Python: >=3.6
Requires-Dist: pandas
Requires-Dist: requests
